[
    {
        "name": "JC01",
        "coords": [
            [
                120.49989610501109,
                32.044845778820694
            ],
            [
                120.49965852902085,
                32.043054010465546
            ]
        ],
        "warnValue": 0
    },
    {
        "name": "JC02",
        "coords": [
            [
                120.51211644811006,
                32.04310480824947
            ],
            [
                120.51157809855385,
                32.04135665004222
            ]
        ],
        "warnValue": 0.18
    },
    {
        "name": "JC03",
        "coords": [
            [
                120.51598399026375,
                32.04244111945512
            ],
            [
                120.51554162835052,
                32.04064910386879
            ]
        ],
        "warnValue": 0.18
    },
    {
        "name": "JC04",
        "coords": [
            [
                120.52163733002358,
                32.040317481106044
            ],
            [
                120.52010747944439,
                32.03901766791365
            ]
        ],
        "warnValue": 0.18
    },
    {
        "name": "JC05",
        "coords": [
            [
                120.52344753736321,
                32.03912224359854
            ],
            [
                120.52202732882418,
                32.037765786589944
            ]
        ],
        "warnValue": 0.18
    },
    {
        "name": "JC06",
        "coords": [
            [
                120.5300568728269,
                32.035076196597906
            ],
            [
                120.52886185568613,
                32.03359585101801
            ]
        ],
        "warnValue": 0.42
    },
    {
        "name": "JC07",
        "coords": [
            [
                120.53577029390934,
                32.03306474923213
            ],
            [
                120.53521759568126,
                32.03132371065091
            ]
        ],
        "warnValue": 0.42
    },
    {
        "name": "JC08",
        "coords": [
            [
                120.54259039936055,
                32.03113531223312
            ],
            [
                120.54191211481913,
                32.0294311450221
            ]
        ],
        "warnValue": 0.42
    },
    {
        "name": "JC09",
        "coords": [
            [
                120.54845619793755,
                32.02942703528161
            ],
            [
                120.547645906125,
                32.027757714058616
            ]
        ],
        "warnValue": 0.18
    },
    {
        "name": "JC10",
        "coords": [
            [
                120.55217332294447,
                32.02819103999115
            ],
            [
                120.55139957273384,
                32.02651468780271
            ]
        ],
        "warnValue": 0.18
    },
    {
        "name": "JC11",
        "coords": [
            [
                120.55987007042168,
                32.0256085153387
            ],
            [
                120.55938372124096,
                32.02385317986381
            ]
        ],
        "warnValue": 0.42
    },
    {
        "name": "JC12",
        "coords": [
            [
                120.56542283954619,
                32.023997421425335
            ],
            [
                120.56490201809913,
                32.022254233310434
            ]
        ],
        "warnValue": 0.18
    }
]